credigraph/__init__.py
credigraph/client.py
credigraph/test/test_API.py
credigraph/utils/__init__.py
credigraph/utils/domain_handler.py
credigraph/utils/string_handler.py
credigraph-0.1.4.dist-info/METADATA
credigraph-0.1.4.dist-info/WHEEL
credigraph-0.1.4.dist-info/top_level.txt
credigraph-0.1.4.dist-info/RECORD
