Metadata-Version: 2.4
Name: credigraph
Version: 0.1.4
Summary: Python client for the CrediGraph API
Author: Complex Data Lab
Project-URL: Homepage, https://huggingface.co/spaces/credi-net/CrediNet
Requires-Dist: build>=1.4.0
Requires-Dist: pytest>=9.0.2
Requires-Dist: requests
Requires-Dist: requests-mock>=1.12.1
Requires-Dist: tldextract>=5.3.1
Requires-Dist: twine>=6.2.0
